flit_ext/__init__.py
flit_ext/version.py
flit_ext-0.0.3.dist-info/entry_points.txt
flit_ext-0.0.3.dist-info/LICENSE
flit_ext-0.0.3.dist-info/WHEEL
flit_ext-0.0.3.dist-info/METADATA
flit_ext-0.0.3.dist-info/RECORD
